pip_requirements_parser.py
pip_requirements_parser-32.0.0.dist-info/AUTHORS.rst
pip_requirements_parser-32.0.0.dist-info/CHANGELOG.rst
pip_requirements_parser-32.0.0.dist-info/METADATA
pip_requirements_parser-32.0.0.dist-info/README.rst
pip_requirements_parser-32.0.0.dist-info/WHEEL
pip_requirements_parser-32.0.0.dist-info/mit.LICENSE
pip_requirements_parser-32.0.0.dist-info/top_level.txt
pip_requirements_parser-32.0.0.dist-info/RECORD
