Metadata-Version: 2.1
Name: pip-requirements-parser
Version: 32.0.0
Summary: pip requirements parser - a mostly correct pip requirements parsing library because it uses pip's own code.
Home-page: https://github.com/nexB/pip-requirements-parser
Author: The pip authors, nexB. Inc. and others
Author-email: info@aboutcode.org
License: MIT
Keywords: utilities pip requirements parser dependencies pypi
Classifier: Development Status :: 5 - Production/Stable
Classifier: Intended Audience :: Developers
Classifier: Programming Language :: Python :: 3
Classifier: Programming Language :: Python :: 3 :: Only
Classifier: Topic :: Software Development
Classifier: Topic :: Utilities
Requires-Python: >=3.6.*
License-File: mit.LICENSE
License-File: AUTHORS.rst
License-File: CHANGELOG.rst
License-File: README.rst
Requires-Dist: packaging (<22.0.0)
Provides-Extra: docs
Requires-Dist: Sphinx (>=3.3.1) ; extra == 'docs'
Requires-Dist: sphinx-rtd-theme (>=0.5.0) ; extra == 'docs'
Requires-Dist: doc8 (>=0.8.1) ; extra == 'docs'
Provides-Extra: testing
Requires-Dist: pytest (!=7.0.0,>=6) ; extra == 'testing'
Requires-Dist: pytest-xdist (>=2) ; extra == 'testing'
Requires-Dist: aboutcode-toolkit (>=6.0.0) ; extra == 'testing'
Requires-Dist: black ; extra == 'testing'
